{"plant_names": [{"entity_candidate": "Tuber melanosporum", "api_query_name": "Tuber melanosporum", "ngram_type": "ngram", "sentences_indices": {"sentence_ID": [{"sent_ID_1": [[10, 11]]}, {"sent_ID_2": [[3, 4]]}, {"sent_ID_240": [[9, 10]]}, {"sent_ID_242": [[12, 13]]}, {"sent_ID_748": [[0, 1]]}, {"sent_ID_749": [[7, 8]]}]}, "id_CoL": "c34d5992fa59049ed388699a67f47d10", "taxon_rank": "Species", "associated_scientific_name": "Tuber melanosporum", "CoL_status": "accepted name", "biblio_reference": "", "url_to_CoL_entry": "http://www.catalogueoflife.org/col/details/species/id/c34d5992fa59049ed388699a67f47d10"}, {"entity_candidate": "fungus", "api_query_name": "fungus", "ngram_type": "unigram", "sentences_indices": {"sentence_ID": [{"sent_ID_3": [17]}, {"sent_ID_4": [70]}, {"sent_ID_245": [32]}]}, "id_CoL": "42fc69f52012560a18ebf69186644f30", "taxon_rank": "Species", "associated_scientific_name": "Stropharia pseudocyanea", "CoL_status": "synonym", "biblio_reference": "Kirk P.M. (2019). Species Fungorum (version Oct 2017). In: Species 2000 & ITIS Catalogue of Life, 29th January 2019 (Roskov Y., Ower G., Orrell T., Nicolson D., Bailly N., Kirk P.M., Bourgoin T., DeWalt R.E., Decock W., Nieukerken E. van, Zarucchi J., Penev L., eds.). Digital resource at www.catalogueoflife.org/col. Species 2000: Naturalis, Leiden, the Netherlands. ISSN 2405-8858.", "url_to_CoL_entry": "http://www.catalogueoflife.org/col/details/species/id/42fc69f52012560a18ebf69186644f30"}, {"entity_candidate": "T. melanosporum", "api_query_name": "T. melanosporum", "ngram_type": "ngram", "sentences_indices": {"sentence_ID": [{"sent_ID_8": [[6, 7]]}, {"sent_ID_244": [[10, 11]]}, {"sent_ID_247": [[17, 18]]}, {"sent_ID_756": [[14, 15]]}]}, "id_CoL": "", "taxon_rank": "", "associated_scientific_name": "", "CoL_status": "", "biblio_reference": "", "url_to_CoL_entry": ""}, {"entity_candidate": "Norway spruce", "api_query_name": "Norway spruce", "ngram_type": "ngram", "sentences_indices": {"sentence_ID": [{"sent_ID_13": [[3, 4]]}, {"sent_ID_393": [[47, 48]]}, {"sent_ID_400": [[11, 12]]}, {"sent_ID_402": [[32, 33]]}]}, "id_CoL": "b9f99a1f126b6b9d3d8c560386dea188", "taxon_rank": "Species", "associated_scientific_name": "Picea abies", "CoL_status": "common name", "biblio_reference": "Farjon A., Gardner M. & Thomas P. (2019). Conifer Database (version Jan 2014). In: Species 2000 & ITIS Catalogue of Life, 29th January 2019 (Roskov Y., Ower G., Orrell T., Nicolson D., Bailly N., Kirk P.M., Bourgoin T., DeWalt R.E., Decock W., Nieukerken E. van, Zarucchi J., Penev L., eds.). Digital resource at www.catalogueoflife.org/col. Species 2000: Naturalis, Leiden, the Netherlands. ISSN 2405-8858.", "url_to_CoL_entry": "http://www.catalogueoflife.org/col/details/species/id/b9f99a1f126b6b9d3d8c560386dea188"}, {"entity_candidate": "Picea abies", "api_query_name": "Picea abies", "ngram_type": "ngram", "sentences_indices": {"sentence_ID": [{"sent_ID_13": [[6, 7]]}, {"sent_ID_391": [[33, 34]]}, {"sent_ID_393": [[44, 45]]}]}, "id_CoL": "b9f99a1f126b6b9d3d8c560386dea188", "taxon_rank": "Species", "associated_scientific_name": "Picea abies", "CoL_status": "accepted name", "biblio_reference": "", "url_to_CoL_entry": "http://www.catalogueoflife.org/col/details/species/id/b9f99a1f126b6b9d3d8c560386dea188"}, {"entity_candidate": "Solanum lycopersicum", "api_query_name": "Solanum lycopersicum", "ngram_type": "ngram", "sentences_indices": {"sentence_ID": [{"sent_ID_23": [[14, 15]]}]}, "id_CoL": "1bdbaf8b5736890f0ee7046d30944cb2", "taxon_rank": "Species", "associated_scientific_name": "Solanum lycopersicum", "CoL_status": "accepted name", "biblio_reference": "", "url_to_CoL_entry": "http://www.catalogueoflife.org/col/details/species/id/1bdbaf8b5736890f0ee7046d30944cb2"}, {"entity_candidate": "tomato", "api_query_name": "tomato", "ngram_type": "unigram", "sentences_indices": {"sentence_ID": [{"sent_ID_24": [23]}, {"sent_ID_25": [2]}, {"sent_ID_31": [18]}, {"sent_ID_179": [28]}, {"sent_ID_758": [9, 14]}, {"sent_ID_759": [3, 17]}, {"sent_ID_763": [4]}, {"sent_ID_766": [21]}, {"sent_ID_936": [12]}, {"sent_ID_937": [30]}, {"sent_ID_939": [13]}, {"sent_ID_940": [1]}]}, "id_CoL": "c9f9a519c1f4586e5bf08cc6eda8f18d", "taxon_rank": "Species", "associated_scientific_name": "Alternaria tomato", "CoL_status": "accepted name", "biblio_reference": "", "url_to_CoL_entry": "http://www.catalogueoflife.org/col/details/species/id/c9f9a519c1f4586e5bf08cc6eda8f18d"}, {"entity_candidate": "potato", "api_query_name": "potato", "ngram_type": "unigram", "sentences_indices": {"sentence_ID": [{"sent_ID_26": [13]}]}, "id_CoL": "7b8c67c4b47a937b27ed4522db4a6f61", "taxon_rank": "Species", "associated_scientific_name": "Badnavirus: Sweet potato pakakuy virus", "CoL_status": "accepted name", "biblio_reference": "", "url_to_CoL_entry": "http://www.catalogueoflife.org/col/details/species/id/7b8c67c4b47a937b27ed4522db4a6f61"}, {"entity_candidate": "Dunaliella tertiolecta", "api_query_name": "Dunaliella tertiolecta", "ngram_type": "ngram", "sentences_indices": {"sentence_ID": [{"sent_ID_37": [[5, 6]]}]}, "id_CoL": "", "taxon_rank": "", "associated_scientific_name": "", "CoL_status": "", "biblio_reference": "", "url_to_CoL_entry": ""}, {"entity_candidate": "Pelargonium x hortorum", "api_query_name": "Pelargonium x", "ngram_type": "ngram", "sentences_indices": {"sentence_ID": [{"sent_ID_41": [[13, 15]]}, {"sent_ID_43": [[28, 30]]}]}, "id_CoL": "", "taxon_rank": "", "associated_scientific_name": "", "CoL_status": "", "biblio_reference": "", "url_to_CoL_entry": ""}, {"entity_candidate": "Pelargonium", "api_query_name": "Pelargonium", "ngram_type": "unigram", "sentences_indices": {"sentence_ID": [{"sent_ID_46": [28]}]}, "id_CoL": "e0c2c0f44acfa8156fbfabc81c3eaa39", "taxon_rank": "Genus", "associated_scientific_name": "Pelargonium", "CoL_status": "accepted name", "biblio_reference": "", "url_to_CoL_entry": "http://www.catalogueoflife.org/col/browse/tree/id/e0c2c0f44acfa8156fbfabc81c3eaa39"}, {"entity_candidate": "barley", "api_query_name": "barley", "ngram_type": "unigram", "sentences_indices": {"sentence_ID": [{"sent_ID_49": [3]}, {"sent_ID_51": [22]}, {"sent_ID_52": [22]}]}, "id_CoL": "7dd00eb8df8b5585c0ff035472ffdd21", "taxon_rank": "Species", "associated_scientific_name": "Bymovirus: Barley mild mosaic virus", "CoL_status": "accepted name", "biblio_reference": "", "url_to_CoL_entry": "http://www.catalogueoflife.org/col/details/species/id/7dd00eb8df8b5585c0ff035472ffdd21"}, {"entity_candidate": "YUCCA", "api_query_name": "YUCCA", "ngram_type": "unigram", "sentences_indices": {"sentence_ID": [{"sent_ID_51": [9]}]}, "id_CoL": "ced2e4e831f288777750a35b5f6892e1", "taxon_rank": "Genus", "associated_scientific_name": "Yucca", "CoL_status": "accepted name", "biblio_reference": "", "url_to_CoL_entry": "http://www.catalogueoflife.org/col/browse/tree/id/ced2e4e831f288777750a35b5f6892e1"}, {"entity_candidate": "Arabidopsis", "api_query_name": "Arabidopsis", "ngram_type": "unigram", "sentences_indices": {"sentence_ID": [{"sent_ID_51": [24]}, {"sent_ID_59": [14]}, {"sent_ID_167": [8]}, {"sent_ID_169": [12]}, {"sent_ID_170": [19]}, {"sent_ID_175": [15]}, {"sent_ID_223": [16]}, {"sent_ID_290": [13]}, {"sent_ID_292": [44]}, {"sent_ID_350": [19]}, {"sent_ID_421": [1]}, {"sent_ID_422": [1]}, {"sent_ID_428": [8]}, {"sent_ID_607": [8]}, {"sent_ID_610": [5]}, {"sent_ID_617": [16]}, {"sent_ID_618": [16]}, {"sent_ID_698": [13]}, {"sent_ID_720": [14]}, {"sent_ID_726": [7]}, {"sent_ID_758": [16]}, {"sent_ID_764": [1]}, {"sent_ID_766": [23]}, {"sent_ID_794": [23]}, {"sent_ID_891": [23]}, {"sent_ID_899": [28]}, {"sent_ID_902": [18]}, {"sent_ID_903": [3]}, {"sent_ID_904": [9]}, {"sent_ID_922": [3]}, {"sent_ID_943": [19]}, {"sent_ID_944": [1]}, {"sent_ID_952": [4]}]}, "id_CoL": "c0d9ccd478facb2b1af4d7b45de074d8", "taxon_rank": "Genus", "associated_scientific_name": "Arabidopsis", "CoL_status": "accepted name", "biblio_reference": "", "url_to_CoL_entry": "http://www.catalogueoflife.org/col/browse/tree/id/c0d9ccd478facb2b1af4d7b45de074d8"}, {"entity_candidate": "Arabidopsis thaliana", "api_query_name": "Arabidopsis thaliana", "ngram_type": "ngram", "sentences_indices": {"sentence_ID": [{"sent_ID_62": [[5, 6]]}, {"sent_ID_127": [[3, 4]]}, {"sent_ID_129": [[1, 2]]}, {"sent_ID_215": [[13, 14]]}, {"sent_ID_218": [[13, 14]]}, {"sent_ID_340": [[0, 1]]}, {"sent_ID_343": [[23, 24]]}, {"sent_ID_363": [[16, 17]]}, {"sent_ID_919": [[14, 15]]}, {"sent_ID_921": [[22, 23]]}]}, "id_CoL": "15f369ef1876a27d77ed279da54f96d2", "taxon_rank": "Species", "associated_scientific_name": "Arabidopsis thaliana", "CoL_status": "accepted name", "biblio_reference": "", "url_to_CoL_entry": "http://www.catalogueoflife.org/col/details/species/id/15f369ef1876a27d77ed279da54f96d2"}, {"entity_candidate": "Lolium perenne L.", "api_query_name": "Lolium perenne", "ngram_type": "ngram", "sentences_indices": {"sentence_ID": [{"sent_ID_71": [[42, 44]]}]}, "id_CoL": "dc54606aa68039678bba5c95e63881ee", "taxon_rank": "Species", "associated_scientific_name": "Lolium perenne", "CoL_status": "accepted name", "biblio_reference": "", "url_to_CoL_entry": "http://www.catalogueoflife.org/col/details/species/id/dc54606aa68039678bba5c95e63881ee"}, {"entity_candidate": "maize", "api_query_name": "maize", "ngram_type": "unigram", "sentences_indices": {"sentence_ID": [{"sent_ID_78": [8]}, {"sent_ID_80": [12]}, {"sent_ID_159": [10]}, {"sent_ID_160": [2]}, {"sent_ID_161": [21]}, {"sent_ID_162": [2, 37]}, {"sent_ID_163": [13]}, {"sent_ID_166": [15]}, {"sent_ID_322": [11]}, {"sent_ID_325": [22]}, {"sent_ID_382": [5]}, {"sent_ID_385": [26]}, {"sent_ID_460": [14]}, {"sent_ID_462": [21]}, {"sent_ID_463": [8]}, {"sent_ID_465": [24]}, {"sent_ID_467": [20]}, {"sent_ID_468": [26]}]}, "id_CoL": "42202999a91d673ffa9fa1eeb6e21b6e", "taxon_rank": "Species", "associated_scientific_name": "Aureusvirus: Maize white line mosaic virus", "CoL_status": "accepted name", "biblio_reference": "", "url_to_CoL_entry": "http://www.catalogueoflife.org/col/details/species/id/42202999a91d673ffa9fa1eeb6e21b6e"}, {"entity_candidate": "Zea mays", "api_query_name": "Zea mays", "ngram_type": "ngram", "sentences_indices": {"sentence_ID": [{"sent_ID_92": [[24, 25]]}, {"sent_ID_160": [[4, 5]]}, {"sent_ID_325": [[24, 25]]}, {"sent_ID_385": [[28, 30]]}, {"sent_ID_462": [[23, 24]]}]}, "id_CoL": "6a7681dfa66bae01e4971c2d9b8c1d61", "taxon_rank": "Species", "associated_scientific_name": "Zea mays", "CoL_status": "accepted name", "biblio_reference": "", "url_to_CoL_entry": "http://www.catalogueoflife.org/col/details/species/id/6a7681dfa66bae01e4971c2d9b8c1d61"}, {"entity_candidate": "S. littoralis", "api_query_name": "S. littoralis", "ngram_type": "ngram", "sentences_indices": {"sentence_ID": [{"sent_ID_95": [[22, 23]]}]}, "id_CoL": "", "taxon_rank": "", "associated_scientific_name": "", "CoL_status": "", "biblio_reference": "", "url_to_CoL_entry": ""}, {"entity_candidate": "wheat", "api_query_name": "wheat", "ngram_type": "unigram", "sentences_indices": {"sentence_ID": [{"sent_ID_99": [24]}, {"sent_ID_105": [10]}, {"sent_ID_186": [19]}, {"sent_ID_191": [12]}, {"sent_ID_267": [12]}, {"sent_ID_268": [5]}, {"sent_ID_270": [12]}, {"sent_ID_276": [12]}, {"sent_ID_285": [9]}, {"sent_ID_286": [47]}, {"sent_ID_624": [28]}, {"sent_ID_627": [9]}, {"sent_ID_632": [10]}, {"sent_ID_698": [28]}]}, "id_CoL": "ffdee901c3d859ff0fd68ad2e648def6", "taxon_rank": "Species", "associated_scientific_name": "Bymovirus: Wheat spindle streak mosaic virus", "CoL_status": "accepted name", "biblio_reference": "", "url_to_CoL_entry": "http://www.catalogueoflife.org/col/details/species/id/ffdee901c3d859ff0fd68ad2e648def6"}, {"entity_candidate": "durum wheat", "api_query_name": "durum wheat", "ngram_type": "ngram", "sentences_indices": {"sentence_ID": [{"sent_ID_100": [[38, 39]]}, {"sent_ID_283": [[23, 24]]}]}, "id_CoL": "530607b46de15d668945cfab3139ff03", "taxon_rank": "Species", "associated_scientific_name": "Triticum turgidum durum", "CoL_status": "synonym", "biblio_reference": "Govaerts R. (ed). For a full list of reviewers see: http://apps.kew.org/wcsp/compilersReviewers.do (2019). WCSP: World Checklist of Selected Plant Families (version Aug 2017). In: Species 2000 & ITIS Catalogue of Life, 29th January 2019 (Roskov Y., Ower G., Orrell T., Nicolson D., Bailly N., Kirk P.M., Bourgoin T., DeWalt R.E., Decock W., Nieukerken E. van, Zarucchi J., Penev L., eds.). Digital resource at www.catalogueoflife.org/col. Species 2000: Naturalis, Leiden, the Netherlands. ISSN 2405-8858.", "url_to_CoL_entry": "http://www.catalogueoflife.org/col/browse/tree/id/530607b46de15d668945cfab3139ff03"}, {"entity_candidate": "Triticum durum", "api_query_name": "Triticum durum", "ngram_type": "ngram", "sentences_indices": {"sentence_ID": [{"sent_ID_100": [[41, 42]]}]}, "id_CoL": "530607b46de15d668945cfab3139ff03", "taxon_rank": "Species", "associated_scientific_name": "Triticum turgidum durum", "CoL_status": "synonym", "biblio_reference": "Govaerts R. (ed). For a full list of reviewers see: http://apps.kew.org/wcsp/compilersReviewers.do (2019). WCSP: World Checklist of Selected Plant Families (version Aug 2017). In: Species 2000 & ITIS Catalogue of Life, 29th January 2019 (Roskov Y., Ower G., Orrell T., Nicolson D., Bailly N., Kirk P.M., Bourgoin T., DeWalt R.E., Decock W., Nieukerken E. van, Zarucchi J., Penev L., eds.). Digital resource at www.catalogueoflife.org/col. Species 2000: Naturalis, Leiden, the Netherlands. ISSN 2405-8858.", "url_to_CoL_entry": "http://www.catalogueoflife.org/col/browse/tree/id/530607b46de15d668945cfab3139ff03"}, {"entity_candidate": "Phaseolus vulgaris", "api_query_name": "Phaseolus vulgaris", "ngram_type": "ngram", "sentences_indices": {"sentence_ID": [{"sent_ID_109": [[21, 22]]}]}, "id_CoL": "ad8bd76996d6e6f90061601610fe6f7d", "taxon_rank": "Species", "associated_scientific_name": "Phaseolus vulgaris", "CoL_status": "accepted name", "biblio_reference": "", "url_to_CoL_entry": "http://www.catalogueoflife.org/col/details/species/id/ad8bd76996d6e6f90061601610fe6f7d"}, {"entity_candidate": "sunflower", "api_query_name": "sunflower", "ngram_type": "unigram", "sentences_indices": {"sentence_ID": [{"sent_ID_119": [26]}, {"sent_ID_526": [13]}, {"sent_ID_527": [23]}]}, "id_CoL": "cdb7f63434b665c4578b0aa78140c3ac", "taxon_rank": "Species", "associated_scientific_name": "Potyvirus: Sunflower chlorotic mottle virus", "CoL_status": "accepted name", "biblio_reference": "", "url_to_CoL_entry": "http://www.catalogueoflife.org/col/details/species/id/cdb7f63434b665c4578b0aa78140c3ac"}, {"entity_candidate": "Helianthus annuus", "api_query_name": "Helianthus annuus", "ngram_type": "ngram", "sentences_indices": {"sentence_ID": [{"sent_ID_119": [[28, 30]]}, {"sent_ID_527": [[25, 26]]}]}, "id_CoL": "f05e095606af8ed79cbec9f488e6dbd9", "taxon_rank": "Species", "associated_scientific_name": "Helianthus annuus", "CoL_status": "accepted name", "biblio_reference": "", "url_to_CoL_entry": "http://www.catalogueoflife.org/col/details/species/id/f05e095606af8ed79cbec9f488e6dbd9"}, {"entity_candidate": "poplar", "api_query_name": "poplar", "ngram_type": "unigram", "sentences_indices": {"sentence_ID": [{"sent_ID_139": [3]}, {"sent_ID_145": [19]}, {"sent_ID_146": [13]}, {"sent_ID_556": [15]}, {"sent_ID_563": [24]}]}, "id_CoL": "316682877654960eb9f0cde735aa510a", "taxon_rank": "Species", "associated_scientific_name": "Australiseiulus poplar", "CoL_status": "accepted name", "biblio_reference": "", "url_to_CoL_entry": "http://www.catalogueoflife.org/col/details/species/id/316682877654960eb9f0cde735aa510a"}, {"entity_candidate": "Nothofagus pumilio", "api_query_name": "Nothofagus pumilio", "ngram_type": "ngram", "sentences_indices": {"sentence_ID": [{"sent_ID_148": [[11, 12]]}, {"sent_ID_150": [[29, 30]]}]}, "id_CoL": "e9408ef4b5a27bc465ab5d25f55695d4", "taxon_rank": "Species", "associated_scientific_name": "Nothofagus pumilio", "CoL_status": "accepted name", "biblio_reference": "", "url_to_CoL_entry": "http://www.catalogueoflife.org/col/details/species/id/e9408ef4b5a27bc465ab5d25f55695d4"}, {"entity_candidate": "N. pumilio", "api_query_name": "N. pumilio", "ngram_type": "ngram", "sentences_indices": {"sentence_ID": [{"sent_ID_157": [[3, 4]]}]}, "id_CoL": "", "taxon_rank": "", "associated_scientific_name": "", "CoL_status": "", "biblio_reference": "", "url_to_CoL_entry": ""}, {"entity_candidate": "corn smut fungus Ustilago maydis", "api_query_name": "corn smut", "ngram_type": "ngram", "sentences_indices": {"sentence_ID": [{"sent_ID_160": [[10, 14]]}]}, "id_CoL": "", "taxon_rank": "", "associated_scientific_name": "", "CoL_status": "", "biblio_reference": "", "url_to_CoL_entry": ""}, {"entity_candidate": "Ustilago maydis", "api_query_name": "Ustilago maydis", "ngram_type": "ngram", "sentences_indices": {"sentence_ID": [{"sent_ID_160": [[13, 14]]}]}, "id_CoL": "124dcba87bb1ee2038adfd7d6388da17", "taxon_rank": "Species", "associated_scientific_name": "Ustilago maydis", "CoL_status": "accepted name", "biblio_reference": "", "url_to_CoL_entry": "http://www.catalogueoflife.org/col/details/species/id/124dcba87bb1ee2038adfd7d6388da17"}, {"entity_candidate": "U. maydis", "api_query_name": "U. maydis", "ngram_type": "ngram", "sentences_indices": {"sentence_ID": [{"sent_ID_162": [[12, 13]]}, {"sent_ID_163": [[6, 7]]}, {"sent_ID_164": [[12, 13]]}, {"sent_ID_165": [[9, 10], [36, 37]]}, {"sent_ID_166": [[21, 22]]}]}, "id_CoL": "", "taxon_rank": "", "associated_scientific_name": "", "CoL_status": "", "biblio_reference": "", "url_to_CoL_entry": ""}, {"entity_candidate": "brome", "api_query_name": "brome", "ngram_type": "unigram", "sentences_indices": {"sentence_ID": [{"sent_ID_162": [30]}]}, "id_CoL": "845c2f541ff3afa98ddcabb1f4b3f87c", "taxon_rank": "Genus", "associated_scientific_name": "Brome", "CoL_status": "accepted name", "biblio_reference": "", "url_to_CoL_entry": "http://www.catalogueoflife.org/col/browse/tree/id/845c2f541ff3afa98ddcabb1f4b3f87c"}, {"entity_candidate": "Potato", "api_query_name": "Potato", "ngram_type": "unigram", "sentences_indices": {"sentence_ID": [{"sent_ID_169": [4]}, {"sent_ID_279": [6]}]}, "id_CoL": "7b8c67c4b47a937b27ed4522db4a6f61", "taxon_rank": "Species", "associated_scientific_name": "Badnavirus: Sweet potato pakakuy virus", "CoL_status": "accepted name", "biblio_reference": "", "url_to_CoL_entry": "http://www.catalogueoflife.org/col/details/species/id/7b8c67c4b47a937b27ed4522db4a6f61"}, {"entity_candidate": "Turnip", "api_query_name": "Turnip", "ngram_type": "unigram", "sentences_indices": {"sentence_ID": [{"sent_ID_171": [7]}]}, "id_CoL": "f1c03bb84510646a23baea21675815c1", "taxon_rank": "Species", "associated_scientific_name": "Carmovirus: Turnip crinkle virus", "CoL_status": "accepted name", "biblio_reference": "", "url_to_CoL_entry": "http://www.catalogueoflife.org/col/details/species/id/f1c03bb84510646a23baea21675815c1"}, {"entity_candidate": "bread wheat", "api_query_name": "bread wheat", "ngram_type": "ngram", "sentences_indices": {"sentence_ID": [{"sent_ID_184": [[23, 24]]}, {"sent_ID_187": [[27, 28]]}]}, "id_CoL": "a028f6f713eaf94d0ebb0590648c5595", "taxon_rank": "Species", "associated_scientific_name": "Triticum aestivum", "CoL_status": "accepted name", "biblio_reference": "", "url_to_CoL_entry": "http://www.catalogueoflife.org/col/details/species/id/a028f6f713eaf94d0ebb0590648c5595"}, {"entity_candidate": "Antirrhinum", "api_query_name": "Antirrhinum", "ngram_type": "unigram", "sentences_indices": {"sentence_ID": [{"sent_ID_192": [17]}, {"sent_ID_194": [12]}, {"sent_ID_201": [11]}]}, "id_CoL": "85aec29ceec241c443debab0d7618f12", "taxon_rank": "Genus", "associated_scientific_name": "Antirrhinum", "CoL_status": "accepted name", "biblio_reference": "", "url_to_CoL_entry": "http://www.catalogueoflife.org/col/browse/tree/id/85aec29ceec241c443debab0d7618f12"}, {"entity_candidate": "Antirrhinum majus", "api_query_name": "Antirrhinum majus", "ngram_type": "ngram", "sentences_indices": {"sentence_ID": [{"sent_ID_195": [[8, 9]]}]}, "id_CoL": "1cb86572ade237b095b1c81a7893fc11", "taxon_rank": "Species", "associated_scientific_name": "Antirrhinum majus", "CoL_status": "accepted name", "biblio_reference": "", "url_to_CoL_entry": "http://www.catalogueoflife.org/col/details/species/id/1cb86572ade237b095b1c81a7893fc11"}, {"entity_candidate": "sugarcane", "api_query_name": "sugarcane", "ngram_type": "unigram", "sentences_indices": {"sentence_ID": [{"sent_ID_206": [9]}, {"sent_ID_207": [1]}]}, "id_CoL": "a04543cd2d4bf3d6e58f7af111400282", "taxon_rank": "Species", "associated_scientific_name": "Badnavirus: Sugarcane bacilliform IM virus", "CoL_status": "accepted name", "biblio_reference": "", "url_to_CoL_entry": "http://www.catalogueoflife.org/col/details/species/id/a04543cd2d4bf3d6e58f7af111400282"}, {"entity_candidate": "Saccharum spp.", "api_query_name": "Saccharum spp.", "ngram_type": "ngram", "sentences_indices": {"sentence_ID": [{"sent_ID_207": [[3, 4]]}]}, "id_CoL": "", "taxon_rank": "", "associated_scientific_name": "", "CoL_status": "", "biblio_reference": "", "url_to_CoL_entry": ""}, {"entity_candidate": "S. officinarum", "api_query_name": "S. officinarum", "ngram_type": "ngram", "sentences_indices": {"sentence_ID": [{"sent_ID_209": [[15, 16]]}]}, "id_CoL": "", "taxon_rank": "", "associated_scientific_name": "", "CoL_status": "", "biblio_reference": "", "url_to_CoL_entry": ""}, {"entity_candidate": "S. spontaneum", "api_query_name": "S. spontaneum", "ngram_type": "ngram", "sentences_indices": {"sentence_ID": [{"sent_ID_209": [[18, 19]]}]}, "id_CoL": "", "taxon_rank": "", "associated_scientific_name": "", "CoL_status": "", "biblio_reference": "", "url_to_CoL_entry": ""}, {"entity_candidate": "Saccharum", "api_query_name": "Saccharum", "ngram_type": "unigram", "sentences_indices": {"sentence_ID": [{"sent_ID_213": [22]}]}, "id_CoL": "b7c52634ee411cdd0acfa202c908c2d6", "taxon_rank": "Genus", "associated_scientific_name": "Saccharum", "CoL_status": "accepted name", "biblio_reference": "", "url_to_CoL_entry": "http://www.catalogueoflife.org/col/browse/tree/id/b7c52634ee411cdd0acfa202c908c2d6"}, {"entity_candidate": "sorghum", "api_query_name": "sorghum", "ngram_type": "unigram", "sentences_indices": {"sentence_ID": [{"sent_ID_213": [26]}]}, "id_CoL": "1ffc1ee3bd72f8ab3a8c198310a6ae72", "taxon_rank": "Genus", "associated_scientific_name": "Sorghum", "CoL_status": "accepted name", "biblio_reference": "", "url_to_CoL_entry": "http://www.catalogueoflife.org/col/browse/tree/id/1ffc1ee3bd72f8ab3a8c198310a6ae72"}, {"entity_candidate": "Andropogonea", "api_query_name": "Andropogonea", "ngram_type": "unigram", "sentences_indices": {"sentence_ID": [{"sent_ID_213": [33]}]}, "id_CoL": "", "taxon_rank": "", "associated_scientific_name": "", "CoL_status": "", "biblio_reference": "", "url_to_CoL_entry": ""}, {"entity_candidate": "A. thaliana", "api_query_name": "A. thaliana", "ngram_type": "ngram", "sentences_indices": {"sentence_ID": [{"sent_ID_223": [[12, 13]]}, {"sent_ID_344": [[4, 5]]}, {"sent_ID_365": [[11, 12]]}, {"sent_ID_371": [[17, 18]]}]}, "id_CoL": "", "taxon_rank": "", "associated_scientific_name": "", "CoL_status": "", "biblio_reference": "", "url_to_CoL_entry": ""}, {"entity_candidate": "Oryza sativa", "api_query_name": "Oryza sativa", "ngram_type": "ngram", "sentences_indices": {"sentence_ID": [{"sent_ID_228": [[23, 24]]}, {"sent_ID_229": [[4, 5]]}, {"sent_ID_633": [[14, 15]]}, {"sent_ID_634": [[14, 15]]}, {"sent_ID_653": [[3, 4]]}, {"sent_ID_769": [[10, 11]]}, {"sent_ID_781": [[19, 20]]}]}, "id_CoL": "6dde3618bacd6befcd443ffd74fea6b7", "taxon_rank": "Species", "associated_scientific_name": "Oryza sativa", "CoL_status": "accepted name", "biblio_reference": "", "url_to_CoL_entry": "http://www.catalogueoflife.org/col/details/species/id/6dde3618bacd6befcd443ffd74fea6b7"}, {"entity_candidate": "rice", "api_query_name": "rice", "ngram_type": "unigram", "sentences_indices": {"sentence_ID": [{"sent_ID_229": [1]}, {"sent_ID_236": [19]}, {"sent_ID_633": [12]}, {"sent_ID_637": [15, 38]}, {"sent_ID_641": [11]}, {"sent_ID_651": [4]}, {"sent_ID_653": [1]}, {"sent_ID_654": [5]}, {"sent_ID_725": [3]}, {"sent_ID_735": [11]}, {"sent_ID_736": [2]}, {"sent_ID_768": [17]}, {"sent_ID_769": [8]}, {"sent_ID_777": [11]}, {"sent_ID_779": [12]}, {"sent_ID_780": [11]}, {"sent_ID_781": [17, 28, 47]}, {"sent_ID_790": [15]}, {"sent_ID_907": [10]}, {"sent_ID_908": [13]}, {"sent_ID_909": [12]}, {"sent_ID_911": [15]}, {"sent_ID_914": [2]}, {"sent_ID_915": [7]}, {"sent_ID_916": [2]}, {"sent_ID_917": [12]}, {"sent_ID_918": [11]}]}, "id_CoL": "0dc73af92748f6ebdbaad1425e4eb920", "taxon_rank": "Species", "associated_scientific_name": "Benyvirus: Rice stripe necrosis virus", "CoL_status": "accepted name", "biblio_reference": "", "url_to_CoL_entry": "http://www.catalogueoflife.org/col/details/species/id/0dc73af92748f6ebdbaad1425e4eb920"}, {"entity_candidate": "Nicotiana benthamiana", "api_query_name": "Nicotiana benthamiana", "ngram_type": "ngram", "sentences_indices": {"sentence_ID": [{"sent_ID_279": [[0, 1]]}, {"sent_ID_762": [[15, 16]]}]}, "id_CoL": "35b3053b2369b8a86b6a1e90f535b457", "taxon_rank": "Species", "associated_scientific_name": "Nicotiana benthamiana", "CoL_status": "accepted name", "biblio_reference": "", "url_to_CoL_entry": "http://www.catalogueoflife.org/col/details/species/id/35b3053b2369b8a86b6a1e90f535b457"}, {"entity_candidate": "perennial grass", "api_query_name": "perennial grass", "ngram_type": "ngram", "sentences_indices": {"sentence_ID": [{"sent_ID_300": [[15, 16]]}, {"sent_ID_302": [[19, 20]]}]}, "id_CoL": "0127461b02eec5ba37b227f303253d29", "taxon_rank": "Species", "associated_scientific_name": "Ehrharta erecta", "CoL_status": "accepted name", "biblio_reference": "", "url_to_CoL_entry": "http://www.catalogueoflife.org/col/details/species/id/0127461b02eec5ba37b227f303253d29"}, {"entity_candidate": "broccoli", "api_query_name": "broccoli", "ngram_type": "unigram", "sentences_indices": {"sentence_ID": [{"sent_ID_314": [5]}, {"sent_ID_315": [3]}, {"sent_ID_318": [20, 40]}, {"sent_ID_321": [3]}]}, "id_CoL": "5dcf4e0f565c14f1ace6cd82986833d5", "taxon_rank": "Species", "associated_scientific_name": "Alternaria broccoli-italicae", "CoL_status": "accepted name", "biblio_reference": "", "url_to_CoL_entry": "http://www.catalogueoflife.org/col/details/species/id/5dcf4e0f565c14f1ace6cd82986833d5"}, {"entity_candidate": "Brassica oleracea var. italica", "api_query_name": "Brassica oleracea", "ngram_type": "ngram", "sentences_indices": {"sentence_ID": [{"sent_ID_315": [[5, 8]]}]}, "id_CoL": "bb2d1f156db5e00f6928a9b5acd5d352", "taxon_rank": "Species", "associated_scientific_name": "Brassica oleracea", "CoL_status": "accepted name", "biblio_reference": "", "url_to_CoL_entry": "http://www.catalogueoflife.org/col/details/species/id/bb2d1f156db5e00f6928a9b5acd5d352"}, {"entity_candidate": "tobacco", "api_query_name": "tobacco", "ngram_type": "unigram", "sentences_indices": {"sentence_ID": [{"sent_ID_322": [16]}, {"sent_ID_325": [6]}, {"sent_ID_326": [25]}, {"sent_ID_330": [6]}, {"sent_ID_331": [26]}, {"sent_ID_686": [11]}, {"sent_ID_689": [8]}, {"sent_ID_698": [26]}, {"sent_ID_898": [3]}]}, "id_CoL": "2996b8ca419efd589c0bbbe053026c2d", "taxon_rank": "Species", "associated_scientific_name": "Alphanecrovirus: Tobacco necrosis virus A", "CoL_status": "accepted name", "biblio_reference": "", "url_to_CoL_entry": "http://www.catalogueoflife.org/col/details/species/id/2996b8ca419efd589c0bbbe053026c2d"}, {"entity_candidate": "Nicotiana tabacum", "api_query_name": "Nicotiana tabacum", "ngram_type": "ngram", "sentences_indices": {"sentence_ID": [{"sent_ID_325": [[8, 9]]}]}, "id_CoL": "77744d364ae1427ae5743c9d6bbd45f2", "taxon_rank": "Species", "associated_scientific_name": "Nicotiana tabacum", "CoL_status": "accepted name", "biblio_reference": "", "url_to_CoL_entry": "http://www.catalogueoflife.org/col/details/species/id/77744d364ae1427ae5743c9d6bbd45f2"}, {"entity_candidate": "Beta", "api_query_name": "Beta", "ngram_type": "unigram", "sentences_indices": {"sentence_ID": [{"sent_ID_326": [16]}]}, "id_CoL": "87cf6a1e49f18ec7f41a1805349328ed", "taxon_rank": "Genus", "associated_scientific_name": "Beta", "CoL_status": "accepted name", "biblio_reference": "", "url_to_CoL_entry": "http://www.catalogueoflife.org/col/browse/tree/id/87cf6a1e49f18ec7f41a1805349328ed"}, {"entity_candidate": "Medicago truncatula", "api_query_name": "Medicago truncatula", "ngram_type": "ngram", "sentences_indices": {"sentence_ID": [{"sent_ID_335": [[5, 6]]}, {"sent_ID_499": [[28, 29]]}]}, "id_CoL": "1b657755d52c3b7075ebe4a372ab2717", "taxon_rank": "Species", "associated_scientific_name": "Medicago truncatula", "CoL_status": "accepted name", "biblio_reference": "", "url_to_CoL_entry": "http://www.catalogueoflife.org/col/details/species/id/1b657755d52c3b7075ebe4a372ab2717"}, {"entity_candidate": "Daucus carota", "api_query_name": "Daucus carota", "ngram_type": "ngram", "sentences_indices": {"sentence_ID": [{"sent_ID_335": [[8, 9]]}]}, "id_CoL": "0973f18d203bffa4ad6ecc320ca27fab", "taxon_rank": "Species", "associated_scientific_name": "Daucus carota", "CoL_status": "accepted name", "biblio_reference": "", "url_to_CoL_entry": "http://www.catalogueoflife.org/col/details/species/id/0973f18d203bffa4ad6ecc320ca27fab"}, {"entity_candidate": "M. truncatula", "api_query_name": "M. truncatula", "ngram_type": "ngram", "sentences_indices": {"sentence_ID": [{"sent_ID_337": [[31, 32]]}, {"sent_ID_502": [[16, 17]]}, {"sent_ID_504": [[12, 13]]}]}, "id_CoL": "", "taxon_rank": "", "associated_scientific_name": "", "CoL_status": "", "biblio_reference": "", "url_to_CoL_entry": ""}, {"entity_candidate": "Ginkgo biloba", "api_query_name": "Ginkgo biloba", "ngram_type": "ngram", "sentences_indices": {"sentence_ID": [{"sent_ID_351": [[7, 8]]}, {"sent_ID_352": [[9, 10]]}]}, "id_CoL": "b0109d3f39b48e77fe739645f3d9d8fa", "taxon_rank": "Species", "associated_scientific_name": "Ginkgo biloba", "CoL_status": "accepted name", "biblio_reference": "", "url_to_CoL_entry": "http://www.catalogueoflife.org/col/details/species/id/b0109d3f39b48e77fe739645f3d9d8fa"}, {"entity_candidate": "G. biloba", "api_query_name": "G. biloba", "ngram_type": "ngram", "sentences_indices": {"sentence_ID": [{"sent_ID_360": [[8, 9]]}]}, "id_CoL": "", "taxon_rank": "", "associated_scientific_name": "", "CoL_status": "", "biblio_reference": "", "url_to_CoL_entry": ""}, {"entity_candidate": "Leavenworthia", "api_query_name": "Leavenworthia", "ngram_type": "unigram", "sentences_indices": {"sentence_ID": [{"sent_ID_362": [13]}, {"sent_ID_372": [13]}]}, "id_CoL": "40630ed1f969ad88a684037db69e18bd", "taxon_rank": "Genus", "associated_scientific_name": "Leavenworthia", "CoL_status": "accepted name", "biblio_reference": "", "url_to_CoL_entry": "http://www.catalogueoflife.org/col/browse/tree/id/40630ed1f969ad88a684037db69e18bd"}, {"entity_candidate": "Brassicaceae", "api_query_name": "Brassicaceae", "ngram_type": "unigram", "sentences_indices": {"sentence_ID": [{"sent_ID_362": [15]}, {"sent_ID_518": [1]}, {"sent_ID_519": [14]}]}, "id_CoL": "12729bb9e290a4c0dbe91734d5db76c3", "taxon_rank": "Family", "associated_scientific_name": "Brassicaceae", "CoL_status": "accepted name", "biblio_reference": "", "url_to_CoL_entry": "http://www.catalogueoflife.org/col/browse/tree/id/12729bb9e290a4c0dbe91734d5db76c3"}, {"entity_candidate": "Leavenworthia crassa", "api_query_name": "Leavenworthia crassa", "ngram_type": "ngram", "sentences_indices": {"sentence_ID": [{"sent_ID_363": [[0, 1]]}]}, "id_CoL": "d44b191d49c14d8ccb9ae55313562f83", "taxon_rank": "Species", "associated_scientific_name": "Leavenworthia crassa", "CoL_status": "accepted name", "biblio_reference": "", "url_to_CoL_entry": "http://www.catalogueoflife.org/col/details/species/id/d44b191d49c14d8ccb9ae55313562f83"}, {"entity_candidate": "L. crassa", "api_query_name": "L. crassa", "ngram_type": "ngram", "sentences_indices": {"sentence_ID": [{"sent_ID_364": [[11, 12]]}, {"sent_ID_371": [[20, 21]]}]}, "id_CoL": "", "taxon_rank": "", "associated_scientific_name": "", "CoL_status": "", "biblio_reference": "", "url_to_CoL_entry": ""}, {"entity_candidate": "Lotus", "api_query_name": "Lotus", "ngram_type": "unigram", "sentences_indices": {"sentence_ID": [{"sent_ID_373": [8]}, {"sent_ID_374": [3]}]}, "id_CoL": "29af9b5ab14c01cb7ff486e1ff3ae748", "taxon_rank": "Species", "associated_scientific_name": "Atylotus lotus", "CoL_status": "accepted name", "biblio_reference": "", "url_to_CoL_entry": "http://www.catalogueoflife.org/col/details/species/id/29af9b5ab14c01cb7ff486e1ff3ae748"}, {"entity_candidate": "Lotus creticus", "api_query_name": "Lotus creticus", "ngram_type": "ngram", "sentences_indices": {"sentence_ID": [{"sent_ID_376": [[35, 36]]}]}, "id_CoL": "ffd390dceb5e6b31cb61466ad971144a", "taxon_rank": "Species", "associated_scientific_name": "Lotus creticus", "CoL_status": "accepted name", "biblio_reference": "", "url_to_CoL_entry": "http://www.catalogueoflife.org/col/details/species/id/ffd390dceb5e6b31cb61466ad971144a"}, {"entity_candidate": "Lotus corniculatus", "api_query_name": "Lotus corniculatus", "ngram_type": "ngram", "sentences_indices": {"sentence_ID": [{"sent_ID_376": [[53, 54]]}]}, "id_CoL": "b3671f4d36bff9e9e8daf8238ae02476", "taxon_rank": "Species", "associated_scientific_name": "Lotus corniculatus", "CoL_status": "accepted name", "biblio_reference": "", "url_to_CoL_entry": "http://www.catalogueoflife.org/col/details/species/id/b3671f4d36bff9e9e8daf8238ae02476"}, {"entity_candidate": "Lotus tenuis", "api_query_name": "Lotus tenuis", "ngram_type": "ngram", "sentences_indices": {"sentence_ID": [{"sent_ID_376": [[56, 57]]}]}, "id_CoL": "d4bb8982ef09c18fc8006ce5d79e9df8", "taxon_rank": "Species", "associated_scientific_name": "Lotus tenuis", "CoL_status": "accepted name", "biblio_reference": "", "url_to_CoL_entry": "http://www.catalogueoflife.org/col/details/species/id/d4bb8982ef09c18fc8006ce5d79e9df8"}, {"entity_candidate": "L. creticus", "api_query_name": "L. creticus", "ngram_type": "ngram", "sentences_indices": {"sentence_ID": [{"sent_ID_377": [[0, 1]]}, {"sent_ID_380": [[8, 9]]}]}, "id_CoL": "", "taxon_rank": "", "associated_scientific_name": "", "CoL_status": "", "biblio_reference": "", "url_to_CoL_entry": ""}, {"entity_candidate": "Fagus sylvatica", "api_query_name": "Fagus sylvatica", "ngram_type": "ngram", "sentences_indices": {"sentence_ID": [{"sent_ID_391": [[27, 28]]}, {"sent_ID_393": [[36, 37]]}]}, "id_CoL": "1f4cac67d34e7473fb5092f2fa66f4d2", "taxon_rank": "Species", "associated_scientific_name": "Fagus sylvatica", "CoL_status": "accepted name", "biblio_reference": "", "url_to_CoL_entry": "http://www.catalogueoflife.org/col/details/species/id/1f4cac67d34e7473fb5092f2fa66f4d2"}, {"entity_candidate": "European beech", "api_query_name": "European beech", "ngram_type": "ngram", "sentences_indices": {"sentence_ID": [{"sent_ID_393": [[39, 40]]}]}, "id_CoL": "1f4cac67d34e7473fb5092f2fa66f4d2", "taxon_rank": "Species", "associated_scientific_name": "Fagus sylvatica", "CoL_status": "accepted name", "biblio_reference": "", "url_to_CoL_entry": "http://www.catalogueoflife.org/col/details/species/id/1f4cac67d34e7473fb5092f2fa66f4d2"}, {"entity_candidate": "Beech", "api_query_name": "Beech", "ngram_type": "unigram", "sentences_indices": {"sentence_ID": [{"sent_ID_395": [14]}, {"sent_ID_398": [10]}]}, "id_CoL": "3602c60f7c91019a2fa119aac75d27e5", "taxon_rank": "Species", "associated_scientific_name": "Eriococcus fagicorticis", "CoL_status": "common name", "biblio_reference": "Ben-Dov Y. & Miller D.R. (2019). ScaleNet: Systematic Database of the Scale Insects of the World (version Dec 2004). In: Species 2000 & ITIS Catalogue of Life, 29th January 2019 (Roskov Y., Ower G., Orrell T., Nicolson D., Bailly N., Kirk P.M., Bourgoin T., DeWalt R.E., Decock W., Nieukerken E. van, Zarucchi J., Penev L., eds.). Digital resource at www.catalogueoflife.org/col. Species 2000: Naturalis, Leiden, the Netherlands. ISSN 2405-8858.", "url_to_CoL_entry": "http://www.catalogueoflife.org/col/details/species/id/3602c60f7c91019a2fa119aac75d27e5"}, {"entity_candidate": "Spruce", "api_query_name": "Spruce", "ngram_type": "unigram", "sentences_indices": {"sentence_ID": [{"sent_ID_395": [20]}, {"sent_ID_398": [15]}]}, "id_CoL": "279d2919a777323ead5947081446be62", "taxon_rank": "Species", "associated_scientific_name": "Elatobium abietinum", "CoL_status": "common name", "biblio_reference": "Favret C. (2019). SF Aphid: Aphid Species File (version 5.0, Jun 2018). In: Species 2000 & ITIS Catalogue of Life, 29th January 2019 (Roskov Y., Ower G., Orrell T., Nicolson D., Bailly N., Kirk P.M., Bourgoin T., DeWalt R.E., Decock W., Nieukerken E. van, Zarucchi J., Penev L., eds.). Digital resource at www.catalogueoflife.org/col. Species 2000: Naturalis, Leiden, the Netherlands. ISSN 2405-8858.", "url_to_CoL_entry": "http://www.catalogueoflife.org/col/details/species/id/279d2919a777323ead5947081446be62"}, {"entity_candidate": "conifers", "api_query_name": "conifers", "ngram_type": "unigram", "sentences_indices": {"sentence_ID": [{"sent_ID_401": [14]}]}, "id_CoL": "", "taxon_rank": "", "associated_scientific_name": "", "CoL_status": "", "biblio_reference": "", "url_to_CoL_entry": ""}, {"entity_candidate": "cucumber", "api_query_name": "cucumber", "ngram_type": "unigram", "sentences_indices": {"sentence_ID": [{"sent_ID_410": [17]}, {"sent_ID_411": [28]}]}, "id_CoL": "57727e4ec6215dc66fa8ff2ecf3cf126", "taxon_rank": "Species", "associated_scientific_name": "Aureusvirus: Cucumber leaf spot virus", "CoL_status": "accepted name", "biblio_reference": "", "url_to_CoL_entry": "http://www.catalogueoflife.org/col/details/species/id/57727e4ec6215dc66fa8ff2ecf3cf126"}, {"entity_candidate": "conifer", "api_query_name": "conifer", "ngram_type": "unigram", "sentences_indices": {"sentence_ID": [{"sent_ID_430": [10]}]}, "id_CoL": "3d4569a61b5aebc3f4569f20663fedcc", "taxon_rank": "Species", "associated_scientific_name": "Acalles conifer", "CoL_status": "provisionally accepted name", "biblio_reference": "", "url_to_CoL_entry": "http://www.catalogueoflife.org/col/details/species/id/3d4569a61b5aebc3f4569f20663fedcc"}, {"entity_candidate": "Pinus sylvestris", "api_query_name": "Pinus sylvestris", "ngram_type": "ngram", "sentences_indices": {"sentence_ID": [{"sent_ID_433": [[23, 24]]}]}, "id_CoL": "4cfb26896653ba917358a0d9ff67d683", "taxon_rank": "Species", "associated_scientific_name": "Pinus sylvestris", "CoL_status": "accepted name", "biblio_reference": "", "url_to_CoL_entry": "http://www.catalogueoflife.org/col/details/species/id/4cfb26896653ba917358a0d9ff67d683"}, {"entity_candidate": "Alnus fruticosa", "api_query_name": "Alnus fruticosa", "ngram_type": "ngram", "sentences_indices": {"sentence_ID": [{"sent_ID_469": [[7, 8]]}, {"sent_ID_472": [[1, 2]]}]}, "id_CoL": "777eb62214ffd30cd648a08488fbe09f", "taxon_rank": "Species", "associated_scientific_name": "Alnus alnobetula fruticosa", "CoL_status": "synonym", "biblio_reference": "Govaerts R. (ed). For a full list of reviewers see: http://apps.kew.org/wcsp/compilersReviewers.do (2019). WCSP: World Checklist of Selected Plant Families (version Aug 2017). In: Species 2000 & ITIS Catalogue of Life, 29th January 2019 (Roskov Y., Ower G., Orrell T., Nicolson D., Bailly N., Kirk P.M., Bourgoin T., DeWalt R.E., Decock W., Nieukerken E. van, Zarucchi J., Penev L., eds.). Digital resource at www.catalogueoflife.org/col. Species 2000: Naturalis, Leiden, the Netherlands. ISSN 2405-8858.", "url_to_CoL_entry": "http://www.catalogueoflife.org/col/browse/tree/id/777eb62214ffd30cd648a08488fbe09f"}, {"entity_candidate": "Alnus", "api_query_name": "Alnus", "ngram_type": "unigram", "sentences_indices": {"sentence_ID": [{"sent_ID_471": [25]}]}, "id_CoL": "47e6cabb0a27b39e3ef5932b8743748e", "taxon_rank": "Genus", "associated_scientific_name": "Alnus", "CoL_status": "accepted name", "biblio_reference": "", "url_to_CoL_entry": "http://www.catalogueoflife.org/col/browse/tree/id/47e6cabb0a27b39e3ef5932b8743748e"}, {"entity_candidate": "Chlamydomonas", "api_query_name": "Chlamydomonas", "ngram_type": "unigram", "sentences_indices": {"sentence_ID": [{"sent_ID_488": [13]}, {"sent_ID_489": [4]}, {"sent_ID_491": [16]}, {"sent_ID_495": [8]}, {"sent_ID_496": [21]}]}, "id_CoL": "48e43edcac0ff4946ee82d1d1ebada88", "taxon_rank": "Genus", "associated_scientific_name": "Chlamydomonas", "CoL_status": "accepted name", "biblio_reference": "", "url_to_CoL_entry": "http://www.catalogueoflife.org/col/browse/tree/id/48e43edcac0ff4946ee82d1d1ebada88"}, {"entity_candidate": "Datisca glomerata", "api_query_name": "Datisca glomerata", "ngram_type": "ngram", "sentences_indices": {"sentence_ID": [{"sent_ID_499": [[21, 22]]}]}, "id_CoL": "2473f3d7f2e84e9f654532b66b19309b", "taxon_rank": "Species", "associated_scientific_name": "Datisca glomerata", "CoL_status": "accepted name", "biblio_reference": "", "url_to_CoL_entry": "http://www.catalogueoflife.org/col/details/species/id/2473f3d7f2e84e9f654532b66b19309b"}, {"entity_candidate": "Cephalanthera damasonium", "api_query_name": "Cephalanthera damasonium", "ngram_type": "ngram", "sentences_indices": {"sentence_ID": [{"sent_ID_507": [[15, 16]]}, {"sent_ID_511": [[4, 5]]}]}, "id_CoL": "1dc388329e486db3d53dd9fdc7f75957", "taxon_rank": "Species", "associated_scientific_name": "Cephalanthera damasonium", "CoL_status": "accepted name", "biblio_reference": "", "url_to_CoL_entry": "http://www.catalogueoflife.org/col/details/species/id/1dc388329e486db3d53dd9fdc7f75957"}, {"entity_candidate": "orchids", "api_query_name": "orchids", "ngram_type": "unigram", "sentences_indices": {"sentence_ID": [{"sent_ID_508": [5]}]}, "id_CoL": "", "taxon_rank": "", "associated_scientific_name": "", "CoL_status": "", "biblio_reference": "", "url_to_CoL_entry": ""}, {"entity_candidate": "C. damasonium", "api_query_name": "C. damasonium", "ngram_type": "ngram", "sentences_indices": {"sentence_ID": [{"sent_ID_512": [[10, 11]]}, {"sent_ID_515": [[7, 8]]}]}, "id_CoL": "", "taxon_rank": "", "associated_scientific_name": "", "CoL_status": "", "biblio_reference": "", "url_to_CoL_entry": ""}, {"entity_candidate": "Barbarea", "api_query_name": "Barbarea", "ngram_type": "unigram", "sentences_indices": {"sentence_ID": [{"sent_ID_517": [5]}, {"sent_ID_524": [16]}]}, "id_CoL": "3f1ee763db1458e43d901c7622745bce", "taxon_rank": "Genus", "associated_scientific_name": "Barbarea", "CoL_status": "accepted name", "biblio_reference": "", "url_to_CoL_entry": "http://www.catalogueoflife.org/col/browse/tree/id/3f1ee763db1458e43d901c7622745bce"}, {"entity_candidate": "Barbarea vulgaris", "api_query_name": "Barbarea vulgaris", "ngram_type": "ngram", "sentences_indices": {"sentence_ID": [{"sent_ID_521": [[4, 5]]}]}, "id_CoL": "261ad3865fb27c4ec936d2e114edcfc7", "taxon_rank": "Species", "associated_scientific_name": "Barbarea vulgaris", "CoL_status": "accepted name", "biblio_reference": "", "url_to_CoL_entry": "http://www.catalogueoflife.org/col/details/species/id/261ad3865fb27c4ec936d2e114edcfc7"}, {"entity_candidate": "Barbarea spp.", "api_query_name": "Barbarea spp.", "ngram_type": "ngram", "sentences_indices": {"sentence_ID": [{"sent_ID_522": [[14, 15]]}, {"sent_ID_523": [[5, 6]]}, {"sent_ID_525": [[31, 32]]}]}, "id_CoL": "", "taxon_rank": "", "associated_scientific_name": "", "CoL_status": "", "biblio_reference": "", "url_to_CoL_entry": ""}, {"entity_candidate": "white spruce", "api_query_name": "white spruce", "ngram_type": "ngram", "sentences_indices": {"sentence_ID": [{"sent_ID_546": [[7, 8]]}, {"sent_ID_548": [[13, 14]]}, {"sent_ID_554": [[10, 11]]}]}, "id_CoL": "7e9c21d9207fb74a3387f103a4e19b1a", "taxon_rank": "Species", "associated_scientific_name": "Picea glauca", "CoL_status": "common name", "biblio_reference": "Farjon A., Gardner M. & Thomas P. (2019). Conifer Database (version Jan 2014). In: Species 2000 & ITIS Catalogue of Life, 29th January 2019 (Roskov Y., Ower G., Orrell T., Nicolson D., Bailly N., Kirk P.M., Bourgoin T., DeWalt R.E., Decock W., Nieukerken E. van, Zarucchi J., Penev L., eds.). Digital resource at www.catalogueoflife.org/col. Species 2000: Naturalis, Leiden, the Netherlands. ISSN 2405-8858.", "url_to_CoL_entry": "http://www.catalogueoflife.org/col/details/species/id/7e9c21d9207fb74a3387f103a4e19b1a"}, {"entity_candidate": "Picea glauca", "api_query_name": "Picea glauca", "ngram_type": "ngram", "sentences_indices": {"sentence_ID": [{"sent_ID_546": [[10, 11]]}, {"sent_ID_548": [[16, 17]]}]}, "id_CoL": "7e9c21d9207fb74a3387f103a4e19b1a", "taxon_rank": "Species", "associated_scientific_name": "Picea glauca", "CoL_status": "accepted name", "biblio_reference": "", "url_to_CoL_entry": "http://www.catalogueoflife.org/col/details/species/id/7e9c21d9207fb74a3387f103a4e19b1a"}, {"entity_candidate": "Populus trichocarpa", "api_query_name": "Populus trichocarpa", "ngram_type": "ngram", "sentences_indices": {"sentence_ID": [{"sent_ID_556": [[17, 20]]}, {"sent_ID_569": [[2, 3]]}]}, "id_CoL": "7a3128867da6d9d0d2c20b8305d2c68a", "taxon_rank": "Species", "associated_scientific_name": "Populus balsamifera trichocarpa", "CoL_status": "synonym", "biblio_reference": "Hassler M. (2019). World Plants: Synonymic Checklists of the Vascular Plants of the World (version Apr 2018). In: Species 2000 & ITIS Catalogue of Life, 29th January 2019 (Roskov Y., Ower G., Orrell T., Nicolson D., Bailly N., Kirk P.M., Bourgoin T., DeWalt R.E., Decock W., Nieukerken E. van, Zarucchi J., Penev L., eds.). Digital resource at www.catalogueoflife.org/col. Species 2000: Naturalis, Leiden, the Netherlands. ISSN 2405-8858.", "url_to_CoL_entry": "http://www.catalogueoflife.org/col/browse/tree/id/7a3128867da6d9d0d2c20b8305d2c68a"}, {"entity_candidate": "Larrea tridentata", "api_query_name": "Larrea tridentata", "ngram_type": "ngram", "sentences_indices": {"sentence_ID": [{"sent_ID_589": [[10, 11]]}, {"sent_ID_592": [[7, 8]]}]}, "id_CoL": "3ef3dffe5e95fbbe2b8f80c745b4c071", "taxon_rank": "Species", "associated_scientific_name": "Larrea tridentata", "CoL_status": "accepted name", "biblio_reference": "", "url_to_CoL_entry": "http://www.catalogueoflife.org/col/details/species/id/3ef3dffe5e95fbbe2b8f80c745b4c071"}, {"entity_candidate": "L. tridentata", "api_query_name": "L. tridentata", "ngram_type": "ngram", "sentences_indices": {"sentence_ID": [{"sent_ID_597": [[31, 32]]}]}, "id_CoL": "", "taxon_rank": "", "associated_scientific_name": "", "CoL_status": "", "biblio_reference": "", "url_to_CoL_entry": ""}, {"entity_candidate": "Triticum aestivum", "api_query_name": "Triticum aestivum", "ngram_type": "ngram", "sentences_indices": {"sentence_ID": [{"sent_ID_627": [[11, 12]]}]}, "id_CoL": "a028f6f713eaf94d0ebb0590648c5595", "taxon_rank": "Species", "associated_scientific_name": "Triticum aestivum", "CoL_status": "accepted name", "biblio_reference": "", "url_to_CoL_entry": "http://www.catalogueoflife.org/col/details/species/id/a028f6f713eaf94d0ebb0590648c5595"}, {"entity_candidate": "Asian rice", "api_query_name": "Asian rice", "ngram_type": "ngram", "sentences_indices": {"sentence_ID": [{"sent_ID_634": [[11, 12]]}]}, "id_CoL": "6dde3618bacd6befcd443ffd74fea6b7", "taxon_rank": "Species", "associated_scientific_name": "Oryza sativa", "CoL_status": "accepted name", "biblio_reference": "", "url_to_CoL_entry": "http://www.catalogueoflife.org/col/details/species/id/6dde3618bacd6befcd443ffd74fea6b7"}, {"entity_candidate": "Oryza rufipogon", "api_query_name": "Oryza rufipogon", "ngram_type": "ngram", "sentences_indices": {"sentence_ID": [{"sent_ID_637": [[47, 48]]}]}, "id_CoL": "4b1f5c5ca90a5e6c14c71e22d10f887a", "taxon_rank": "Species", "associated_scientific_name": "Oryza rufipogon", "CoL_status": "accepted name", "biblio_reference": "", "url_to_CoL_entry": "http://www.catalogueoflife.org/col/details/species/id/4b1f5c5ca90a5e6c14c71e22d10f887a"}, {"entity_candidate": "japonica rice", "api_query_name": "japonica rice", "ngram_type": "ngram", "sentences_indices": {"sentence_ID": [{"sent_ID_641": [[32, 33]]}]}, "id_CoL": "", "taxon_rank": "", "associated_scientific_name": "", "CoL_status": "", "biblio_reference": "", "url_to_CoL_entry": ""}, {"entity_candidate": "Artemisia annua", "api_query_name": "Artemisia annua", "ngram_type": "ngram", "sentences_indices": {"sentence_ID": [{"sent_ID_642": [[16, 17]]}, {"sent_ID_643": [[15, 16]]}]}, "id_CoL": "d6bf1c95e9907cdaeb240bf211dcfc42", "taxon_rank": "Species", "associated_scientific_name": "Artemisia annua", "CoL_status": "accepted name", "biblio_reference": "", "url_to_CoL_entry": "http://www.catalogueoflife.org/col/details/species/id/d6bf1c95e9907cdaeb240bf211dcfc42"}, {"entity_candidate": "A. annua", "api_query_name": "A. annua", "ngram_type": "ngram", "sentences_indices": {"sentence_ID": [{"sent_ID_644": [[23, 24]]}, {"sent_ID_649": [[17, 18]]}]}, "id_CoL": "", "taxon_rank": "", "associated_scientific_name": "", "CoL_status": "", "biblio_reference": "", "url_to_CoL_entry": ""}, {"entity_candidate": "water rice", "api_query_name": "water rice", "ngram_type": "ngram", "sentences_indices": {"sentence_ID": [{"sent_ID_658": [[10, 11]]}]}, "id_CoL": "6a288a97eaf8cb62bee8ba895bee4d7d", "taxon_rank": "Species", "associated_scientific_name": "Sigmodontomys alfari", "CoL_status": "common name", "biblio_reference": "Tom Orrell (custodian), Dave Nicolson (ed). (2019). ITIS Global: The Integrated Taxonomic Information System (version Jun 2017). In: Species 2000 & ITIS Catalogue of Life, 29th January 2019 (Roskov Y., Ower G., Orrell T., Nicolson D., Bailly N., Kirk P.M., Bourgoin T., DeWalt R.E., Decock W., Nieukerken E. van, Zarucchi J., Penev L., eds.). Digital resource at www.catalogueoflife.org/col. Species 2000: Naturalis, Leiden, the Netherlands. ISSN 2405-8858.", "url_to_CoL_entry": "http://www.catalogueoflife.org/col/details/species/id/6a288a97eaf8cb62bee8ba895bee4d7d"}, {"entity_candidate": "lowland rice", "api_query_name": "lowland rice", "ngram_type": "ngram", "sentences_indices": {"sentence_ID": [{"sent_ID_659": [[8, 9]]}]}, "id_CoL": "6dde3618bacd6befcd443ffd74fea6b7", "taxon_rank": "Species", "associated_scientific_name": "Oryza sativa", "CoL_status": "accepted name", "biblio_reference": "", "url_to_CoL_entry": "http://www.catalogueoflife.org/col/details/species/id/6dde3618bacd6befcd443ffd74fea6b7"}, {"entity_candidate": "Citrus", "api_query_name": "Citrus", "ngram_type": "unigram", "sentences_indices": {"sentence_ID": [{"sent_ID_706": [4]}, {"sent_ID_709": [7]}]}, "id_CoL": "5e97405695bd7c655af7ae067f107730", "taxon_rank": "Genus", "associated_scientific_name": "Citrus", "CoL_status": "accepted name", "biblio_reference": "", "url_to_CoL_entry": "http://www.catalogueoflife.org/col/browse/tree/id/5e97405695bd7c655af7ae067f107730"}, {"entity_candidate": "Rice", "api_query_name": "Rice", "ngram_type": "unigram", "sentences_indices": {"sentence_ID": [{"sent_ID_726": [0]}]}, "id_CoL": "0dc73af92748f6ebdbaad1425e4eb920", "taxon_rank": "Species", "associated_scientific_name": "Benyvirus: Rice stripe necrosis virus", "CoL_status": "accepted name", "biblio_reference": "", "url_to_CoL_entry": "http://www.catalogueoflife.org/col/details/species/id/0dc73af92748f6ebdbaad1425e4eb920"}, {"entity_candidate": "blight", "api_query_name": "blight", "ngram_type": "unigram", "sentences_indices": {"sentence_ID": [{"sent_ID_728": [33]}]}, "id_CoL": "5c51e7892c2f0c25c0cf1d319c823e18", "taxon_rank": "Species", "associated_scientific_name": "Blitum capitatum", "CoL_status": "common name", "biblio_reference": "Hassler M. (2019). World Plants: Synonymic Checklists of the Vascular Plants of the World (version Apr 2018). In: Species 2000 & ITIS Catalogue of Life, 29th January 2019 (Roskov Y., Ower G., Orrell T., Nicolson D., Bailly N., Kirk P.M., Bourgoin T., DeWalt R.E., Decock W., Nieukerken E. van, Zarucchi J., Penev L., eds.). Digital resource at www.catalogueoflife.org/col. Species 2000: Naturalis, Leiden, the Netherlands. ISSN 2405-8858.", "url_to_CoL_entry": "http://www.catalogueoflife.org/col/details/species/id/5c51e7892c2f0c25c0cf1d319c823e18"}, {"entity_candidate": "Lotus japonicus", "api_query_name": "Lotus japonicus", "ngram_type": "ngram", "sentences_indices": {"sentence_ID": [{"sent_ID_737": [[5, 6]]}, {"sent_ID_739": [[29, 30]]}]}, "id_CoL": "b5007f94b541d2c62659b58eb17b1fcf", "taxon_rank": "Species", "associated_scientific_name": "Lotus corniculatus corniculatus", "CoL_status": "synonym", "biblio_reference": "Roskov Y., Zarucchi J., Novoselova M. & Bisby F.(\u2020) (eds). (2019). ILDIS World Database of Legumes (version 12, May 2014). In: Species 2000 & ITIS Catalogue of Life, 29th January 2019 (Roskov Y., Ower G., Orrell T., Nicolson D., Bailly N., Kirk P.M., Bourgoin T., DeWalt R.E., Decock W., Nieukerken E. van, Zarucchi J., Penev L., eds.). Digital resource at www.catalogueoflife.org/col. Species 2000: Naturalis, Leiden, the Netherlands. ISSN 2405-8858.", "url_to_CoL_entry": "http://www.catalogueoflife.org/col/browse/tree/id/b5007f94b541d2c62659b58eb17b1fcf"}, {"entity_candidate": "L. japonicus", "api_query_name": "L. japonicus", "ngram_type": "ngram", "sentences_indices": {"sentence_ID": [{"sent_ID_742": [[6, 7]]}, {"sent_ID_746": [[5, 6]]}]}, "id_CoL": "", "taxon_rank": "", "associated_scientific_name": "", "CoL_status": "", "biblio_reference": "", "url_to_CoL_entry": ""}, {"entity_candidate": "oak", "api_query_name": "oak", "ngram_type": "unigram", "sentences_indices": {"sentence_ID": [{"sent_ID_806": [17]}]}, "id_CoL": "80d71ce9c0bb4895fd7a33646b057dbe", "taxon_rank": "Species", "associated_scientific_name": "Dysphania botrys", "CoL_status": "common name", "biblio_reference": "Hassler M. (2019). World Plants: Synonymic Checklists of the Vascular Plants of the World (version Apr 2018). In: Species 2000 & ITIS Catalogue of Life, 29th January 2019 (Roskov Y., Ower G., Orrell T., Nicolson D., Bailly N., Kirk P.M., Bourgoin T., DeWalt R.E., Decock W., Nieukerken E. van, Zarucchi J., Penev L., eds.). Digital resource at www.catalogueoflife.org/col. Species 2000: Naturalis, Leiden, the Netherlands. ISSN 2405-8858.", "url_to_CoL_entry": "http://www.catalogueoflife.org/col/details/species/id/80d71ce9c0bb4895fd7a33646b057dbe"}, {"entity_candidate": "Quercus petraea", "api_query_name": "Quercus petraea", "ngram_type": "ngram", "sentences_indices": {"sentence_ID": [{"sent_ID_806": [[20, 21]]}]}, "id_CoL": "e577d3919c58fa427630e652253c5105", "taxon_rank": "Species", "associated_scientific_name": "Quercus petraea", "CoL_status": "accepted name", "biblio_reference": "", "url_to_CoL_entry": "http://www.catalogueoflife.org/col/details/species/id/e577d3919c58fa427630e652253c5105"}, {"entity_candidate": "Alliaria petiolata", "api_query_name": "Alliaria petiolata", "ngram_type": "ngram", "sentences_indices": {"sentence_ID": [{"sent_ID_812": [[11, 12]]}, {"sent_ID_815": [[13, 14]]}]}, "id_CoL": "d8254749384e599ec16d50b9b4ca4ff8", "taxon_rank": "Species", "associated_scientific_name": "Alliaria petiolata", "CoL_status": "accepted name", "biblio_reference": "", "url_to_CoL_entry": "http://www.catalogueoflife.org/col/details/species/id/d8254749384e599ec16d50b9b4ca4ff8"}, {"entity_candidate": "A. petiolata", "api_query_name": "A. petiolata", "ngram_type": "ngram", "sentences_indices": {"sentence_ID": [{"sent_ID_815": [[28, 29]]}, {"sent_ID_817": [[9, 10]]}]}, "id_CoL": "", "taxon_rank": "", "associated_scientific_name": "", "CoL_status": "", "biblio_reference": "", "url_to_CoL_entry": ""}, {"entity_candidate": "Rumex palustris", "api_query_name": "Rumex palustris", "ngram_type": "ngram", "sentences_indices": {"sentence_ID": [{"sent_ID_826": [[22, 23]]}]}, "id_CoL": "25894ec9d06e572fd97d6c9e47aac9f5", "taxon_rank": "Species", "associated_scientific_name": "Rumex palustris", "CoL_status": "accepted name", "biblio_reference": "", "url_to_CoL_entry": "http://www.catalogueoflife.org/col/details/species/id/25894ec9d06e572fd97d6c9e47aac9f5"}, {"entity_candidate": "Lauraceae", "api_query_name": "Lauraceae", "ngram_type": "unigram", "sentences_indices": {"sentence_ID": [{"sent_ID_834": [24]}]}, "id_CoL": "3d4134f73d901b0ad4ce2d3859e4917e", "taxon_rank": "Family", "associated_scientific_name": "Lauraceae", "CoL_status": "accepted name", "biblio_reference": "", "url_to_CoL_entry": "http://www.catalogueoflife.org/col/browse/tree/id/3d4134f73d901b0ad4ce2d3859e4917e"}, {"entity_candidate": "Thlaspi caerulescens", "api_query_name": "Thlaspi caerulescens", "ngram_type": "ngram", "sentences_indices": {"sentence_ID": [{"sent_ID_857": [[16, 17]]}, {"sent_ID_859": [[12, 13]]}]}, "id_CoL": "e50b241a3f9f9cb262359b71589d62d9", "taxon_rank": "Species", "associated_scientific_name": "Noccaea caerulescens caerulescens", "CoL_status": "synonym", "biblio_reference": "Warwick S.I., Francis A. & Al-Shehbaz I.A. (2019). Brassicaceae species checklist and database (version 2, Oct 2009). In: Species 2000 & ITIS Catalogue of Life, 29th January 2019 (Roskov Y., Ower G., Orrell T., Nicolson D., Bailly N., Kirk P.M., Bourgoin T., DeWalt R.E., Decock W., Nieukerken E. van, Zarucchi J., Penev L., eds.). Digital resource at www.catalogueoflife.org/col. Species 2000: Naturalis, Leiden, the Netherlands. ISSN 2405-8858.", "url_to_CoL_entry": "http://www.catalogueoflife.org/col/browse/tree/id/e50b241a3f9f9cb262359b71589d62d9"}, {"entity_candidate": "sycamore", "api_query_name": "sycamore", "ngram_type": "unigram", "sentences_indices": {"sentence_ID": [{"sent_ID_870": [17]}]}, "id_CoL": "83e7b801a1d54f8c4c047ab07213045b", "taxon_rank": "Species", "associated_scientific_name": "Chionaspis platani", "CoL_status": "common name", "biblio_reference": "Ben-Dov Y. & Miller D.R. (2019). ScaleNet: Systematic Database of the Scale Insects of the World (version Dec 2004). In: Species 2000 & ITIS Catalogue of Life, 29th January 2019 (Roskov Y., Ower G., Orrell T., Nicolson D., Bailly N., Kirk P.M., Bourgoin T., DeWalt R.E., Decock W., Nieukerken E. van, Zarucchi J., Penev L., eds.). Digital resource at www.catalogueoflife.org/col. Species 2000: Naturalis, Leiden, the Netherlands. ISSN 2405-8858.", "url_to_CoL_entry": "http://www.catalogueoflife.org/col/details/species/id/83e7b801a1d54f8c4c047ab07213045b"}, {"entity_candidate": "Acer pseudoplatanus", "api_query_name": "Acer pseudoplatanus", "ngram_type": "ngram", "sentences_indices": {"sentence_ID": [{"sent_ID_870": [[19, 20]]}]}, "id_CoL": "514c8a16507ccd6d5f57d5c5206b50f4", "taxon_rank": "Species", "associated_scientific_name": "Acer pseudoplatanus", "CoL_status": "accepted name", "biblio_reference": "", "url_to_CoL_entry": "http://www.catalogueoflife.org/col/details/species/id/514c8a16507ccd6d5f57d5c5206b50f4"}, {"entity_candidate": "Cryptantha flava", "api_query_name": "Cryptantha flava", "ngram_type": "ngram", "sentences_indices": {"sentence_ID": [{"sent_ID_881": [[15, 16]]}]}, "id_CoL": "44605b4acdf9e90b1b11fa61647e1e23", "taxon_rank": "Species", "associated_scientific_name": "Oreocarya flava", "CoL_status": "synonym", "biblio_reference": "Hassler M. (2019). World Plants: Synonymic Checklists of the Vascular Plants of the World (version Apr 2018). In: Species 2000 & ITIS Catalogue of Life, 29th January 2019 (Roskov Y., Ower G., Orrell T., Nicolson D., Bailly N., Kirk P.M., Bourgoin T., DeWalt R.E., Decock W., Nieukerken E. van, Zarucchi J., Penev L., eds.). Digital resource at www.catalogueoflife.org/col. Species 2000: Naturalis, Leiden, the Netherlands. ISSN 2405-8858.", "url_to_CoL_entry": "http://www.catalogueoflife.org/col/details/species/id/44605b4acdf9e90b1b11fa61647e1e23"}, {"entity_candidate": "Boraginaceae", "api_query_name": "Boraginaceae", "ngram_type": "unigram", "sentences_indices": {"sentence_ID": [{"sent_ID_881": [18]}]}, "id_CoL": "aad64a79379a611cf3f368c57bcaa6f6", "taxon_rank": "Family", "associated_scientific_name": "Boraginaceae", "CoL_status": "accepted name", "biblio_reference": "", "url_to_CoL_entry": "http://www.catalogueoflife.org/col/browse/tree/id/aad64a79379a611cf3f368c57bcaa6f6"}, {"entity_candidate": "Brassica napus", "api_query_name": "Brassica napus", "ngram_type": "ngram", "sentences_indices": {"sentence_ID": [{"sent_ID_887": [[3, 4]]}, {"sent_ID_890": [[24, 25]]}]}, "id_CoL": "aa81effaf576158482694861ac8495b3", "taxon_rank": "Species", "associated_scientific_name": "Brassica napus", "CoL_status": "accepted name", "biblio_reference": "", "url_to_CoL_entry": "http://www.catalogueoflife.org/col/details/species/id/aa81effaf576158482694861ac8495b3"}, {"entity_candidate": "rapeseed", "api_query_name": "rapeseed", "ngram_type": "unigram", "sentences_indices": {"sentence_ID": [{"sent_ID_890": [22]}]}, "id_CoL": "aa81effaf576158482694861ac8495b3", "taxon_rank": "Species", "associated_scientific_name": "Brassica napus", "CoL_status": "accepted name", "biblio_reference": "", "url_to_CoL_entry": "http://www.catalogueoflife.org/col/details/species/id/aa81effaf576158482694861ac8495b3"}, {"entity_candidate": "B. napus", "api_query_name": "B. napus", "ngram_type": "ngram", "sentences_indices": {"sentence_ID": [{"sent_ID_892": [[14, 15]]}, {"sent_ID_896": [[8, 9]]}]}, "id_CoL": "", "taxon_rank": "", "associated_scientific_name": "", "CoL_status": "", "biblio_reference": "", "url_to_CoL_entry": ""}, {"entity_candidate": "lettuce", "api_query_name": "lettuce", "ngram_type": "unigram", "sentences_indices": {"sentence_ID": [{"sent_ID_936": [10]}, {"sent_ID_937": [5, 28]}, {"sent_ID_941": [10]}]}, "id_CoL": "bf8552360b3bdbee1032909948fb94c4", "taxon_rank": "Species", "associated_scientific_name": "Crinivirus: Lettuce chlorosis virus", "CoL_status": "accepted name", "biblio_reference": "", "url_to_CoL_entry": "http://www.catalogueoflife.org/col/details/species/id/bf8552360b3bdbee1032909948fb94c4"}]}